docs/conf.py
notebook/test_register_err_corr_form.py
obsarray/__init__.py
obsarray/_version.py
obsarray/err_corr.py
obsarray/flag_accessor.py
obsarray/unc_accessor.py
obsarray/utils.py
obsarray/templater/__init__.py
obsarray/templater/dataset_util.py
obsarray/templater/dstemplater.py
obsarray/templater/dswriter.py
obsarray/templater/template_util.py
obsarray/templater/tests/__init__.py
obsarray/templater/tests/test_dataset_util.py
obsarray/templater/tests/test_dswriter.py
obsarray/templater/tests/test_template_util.py
obsarray/test/__init__.py
obsarray/test/test_err_corr_forms.py
obsarray/test/test_flag_accessor.py
obsarray/test/test_unc_accessor.py
obsarray/test/test_utils.py
obsarray-1.0.3.dist-info/licenses/LICENSE
obsarray-1.0.3.dist-info/METADATA
obsarray-1.0.3.dist-info/WHEEL
obsarray-1.0.3.dist-info/top_level.txt
obsarray-1.0.3.dist-info/RECORD
