Metadata-Version: 2.4
Name: obsarray
Version: 1.0.3
Summary: Measurement data handling in Python
Author-email: CoMet Toolkit Team <team@comet-toolkit.org>
Project-URL: Homepage, https://github.com/comet-toolkit/obsarray
Requires-Python: >=3.8
License-File: LICENSE
Requires-Dist: comet_maths
Requires-Dist: netcdf4
Requires-Dist: xarray
Provides-Extra: dev
Requires-Dist: pre-commit; extra == "dev"
Requires-Dist: tox; extra == "dev"
Requires-Dist: sphinx; extra == "dev"
Requires-Dist: sphinx_design; extra == "dev"
Requires-Dist: sphinx_book_theme; extra == "dev"
Requires-Dist: ipython; extra == "dev"
Requires-Dist: sphinx_autosummary_accessors; extra == "dev"
Dynamic: license-file
